<?xml version="1.0" encoding="UTF-8"?>
<NNETWORK xmlns:xsi="http://www.w3.org/2001/XMLSchema-instance" xsi:noNamespaceSchemaLocation="ANNeML.xsd" NNET_NAME="AFootball_AF613NNet">
	<SUBNET NNET_V2="0.85" SNET_NAME="AFootball_AF613NNet_logsig" ADJUST_LOCK="0">
		<LAYER LAYER_NAME="INPUT" TRANSFER_FUNCTION="2">
			<NEURODE N_ID="IN001" ACTIVE="-1" ACTIVITY="0.0" BIAS="0.00" CNAME="HOME ypg" NNET_V4="0.0">
					<SYNAPSE WEIGHT="1.00" ORG_NEURODE="INPUT" />
			</NEURODE>
			<NEURODE N_ID="IN002" ACTIVE="-1" ACTIVITY="0.0" BIAS="0.00" CNAME="HOME def ypg" NNET_V4="0.0">
					<SYNAPSE WEIGHT="1.00" ORG_NEURODE="INPUT" />
			</NEURODE>
			<NEURODE N_ID="IN003" ACTIVE="-1" ACTIVITY="0.0" BIAS="0.00" CNAME="HOME t/o ratio" NNET_V4="0.0">
					<SYNAPSE WEIGHT="1.00" ORG_NEURODE="INPUT" />
			</NEURODE>
			<NEURODE N_ID="IN004" ACTIVE="-1" ACTIVITY="0.0" BIAS="0.00" CNAME="HOME QB rating" NNET_V4="0.0">
					<SYNAPSE WEIGHT="1.00" ORG_NEURODE="INPUT" />
			</NEURODE>
			<NEURODE N_ID="IN005" ACTIVE="-1" ACTIVITY="0.0" BIAS="0.00" CNAME="HOME ppg" NNET_V4="0.0">
					<SYNAPSE WEIGHT="1.00" ORG_NEURODE="INPUT" />
			</NEURODE>
			<NEURODE N_ID="IN006" ACTIVE="-1" ACTIVITY="0.0" BIAS="0.00" CNAME="HOME ppg allowed" NNET_V4="0.0">
					<SYNAPSE WEIGHT="1.00" ORG_NEURODE="INPUT" />
			</NEURODE>
			<NEURODE N_ID="IN007" ACTIVE="-1" ACTIVITY="0.0" BIAS="0.00" CNAME="AWAY ypg" NNET_V4="0.0">
					<SYNAPSE WEIGHT="1.00" ORG_NEURODE="INPUT" />
			</NEURODE>
			<NEURODE N_ID="IN008" ACTIVE="-1" ACTIVITY="0.0" BIAS="0.00" CNAME="AWAY def ypg" NNET_V4="0.0">
					<SYNAPSE WEIGHT="1.00" ORG_NEURODE="INPUT" />
			</NEURODE>
			<NEURODE N_ID="IN009" ACTIVE="-1" ACTIVITY="0.0" BIAS="0.00" CNAME="AWAY t/o ratio" NNET_V4="0.0">
					<SYNAPSE WEIGHT="1.00" ORG_NEURODE="INPUT" />
			</NEURODE>
			<NEURODE N_ID="IN010" ACTIVE="-1" ACTIVITY="0.0" BIAS="0.00" CNAME="AWAY QB rating" NNET_V4="0.0">
					<SYNAPSE WEIGHT="1.00" ORG_NEURODE="INPUT" />
			</NEURODE>
			<NEURODE N_ID="IN011" ACTIVE="-1" ACTIVITY="0.0" BIAS="0.00" CNAME="AWAY ppg" NNET_V4="0.0">
					<SYNAPSE WEIGHT="1.00" ORG_NEURODE="INPUT" />
			</NEURODE>
			<NEURODE N_ID="IN012" ACTIVE="-1" ACTIVITY="0.0" BIAS="0.00" CNAME="AWAY ppg allowed" NNET_V4="0.0">
					<SYNAPSE WEIGHT="1.00" ORG_NEURODE="INPUT" />
			</NEURODE>
		</LAYER>
		<LAYER LAYER_NAME="HIDDEN" TRANSFER_FUNCTION="2">
			<NEURODE N_ID="N001" ACTIVE="-1" ACTIVITY="0.0" BIAS="-0.1220" CNAME="hidden 1" NNET_V4="0.0">
					<SYNAPSE WEIGHT="0.9175" ORG_NEURODE="IN001" />
					<SYNAPSE WEIGHT="0.8520" ORG_NEURODE="IN002" />
					<SYNAPSE WEIGHT="-0.1980" ORG_NEURODE="IN003" />
					<SYNAPSE WEIGHT="-0.1373" ORG_NEURODE="IN004" />
					<SYNAPSE WEIGHT="0.5016" ORG_NEURODE="IN005" />
					<SYNAPSE WEIGHT="0.8844" ORG_NEURODE="IN006" />
					<SYNAPSE WEIGHT="-0.5296" ORG_NEURODE="IN007" />
					<SYNAPSE WEIGHT="0.9584" ORG_NEURODE="IN008" />
					<SYNAPSE WEIGHT="-0.2023" ORG_NEURODE="IN009" />
					<SYNAPSE WEIGHT="0.4433" ORG_NEURODE="IN010" />
					<SYNAPSE WEIGHT="-0.5566" ORG_NEURODE="IN011" />
					<SYNAPSE WEIGHT="0.5121" ORG_NEURODE="IN012" />					
			</NEURODE>
			<NEURODE N_ID="N002" ACTIVE="-1" ACTIVITY="0.0" BIAS="-0.4693" CNAME="hidden 2" NNET_V4="0.0">
					<SYNAPSE WEIGHT="0.5432" ORG_NEURODE="IN001" />
					<SYNAPSE WEIGHT="-0.0489" ORG_NEURODE="IN002" />
					<SYNAPSE WEIGHT="-0.5514" ORG_NEURODE="IN003" />
					<SYNAPSE WEIGHT="0.3548" ORG_NEURODE="IN004" />
					<SYNAPSE WEIGHT="0.7173" ORG_NEURODE="IN005" />
					<SYNAPSE WEIGHT="0.9412" ORG_NEURODE="IN006" />
					<SYNAPSE WEIGHT="-0.0511" ORG_NEURODE="IN007" />
					<SYNAPSE WEIGHT="0.8896" ORG_NEURODE="IN008" />
					<SYNAPSE WEIGHT="0.2040" ORG_NEURODE="IN009" />
					<SYNAPSE WEIGHT="-0.5979" ORG_NEURODE="IN010" />
					<SYNAPSE WEIGHT="-0.6533" ORG_NEURODE="IN011" />
					<SYNAPSE WEIGHT="-0.6529" ORG_NEURODE="IN012" />					
			</NEURODE>
			<NEURODE N_ID="N003" ACTIVE="-1" ACTIVITY="0.0" BIAS="0.6112" CNAME="hidden 3" NNET_V4="0.0">
					<SYNAPSE WEIGHT="0.1895" ORG_NEURODE="IN001" />
					<SYNAPSE WEIGHT="0.0950" ORG_NEURODE="IN002" />
					<SYNAPSE WEIGHT="0.2353" ORG_NEURODE="IN003" />
					<SYNAPSE WEIGHT="-0.9988" ORG_NEURODE="IN004" />
					<SYNAPSE WEIGHT="-0.5971" ORG_NEURODE="IN005" />
					<SYNAPSE WEIGHT="0.0486" ORG_NEURODE="IN006" />
					<SYNAPSE WEIGHT="0.3391" ORG_NEURODE="IN007" />
					<SYNAPSE WEIGHT="0.1599" ORG_NEURODE="IN008" />
					<SYNAPSE WEIGHT="-0.9381" ORG_NEURODE="IN009" />
					<SYNAPSE WEIGHT="0.1728" ORG_NEURODE="IN010" />
					<SYNAPSE WEIGHT="-0.2288" ORG_NEURODE="IN011" />
					<SYNAPSE WEIGHT="-0.9422" ORG_NEURODE="IN012" />					
			</NEURODE>
			<NEURODE N_ID="N004" ACTIVE="-1" ACTIVITY="0.0" BIAS="0.3065" CNAME="hidden 4" NNET_V4="0.0">
					<SYNAPSE WEIGHT="-0.0002" ORG_NEURODE="IN001" />
					<SYNAPSE WEIGHT="0.9487" ORG_NEURODE="IN002" />
					<SYNAPSE WEIGHT="-0.5399" ORG_NEURODE="IN003" />
					<SYNAPSE WEIGHT="-0.2488" ORG_NEURODE="IN004" />
					<SYNAPSE WEIGHT="0.0925" ORG_NEURODE="IN005" />
					<SYNAPSE WEIGHT="-0.7411" ORG_NEURODE="IN006" />
					<SYNAPSE WEIGHT="0.8182" ORG_NEURODE="IN007" />
					<SYNAPSE WEIGHT="0.5178" ORG_NEURODE="IN008" />
					<SYNAPSE WEIGHT="0.8285" ORG_NEURODE="IN009" />
					<SYNAPSE WEIGHT="0.5478" ORG_NEURODE="IN010" />
					<SYNAPSE WEIGHT="0.5604" ORG_NEURODE="IN011" />
					<SYNAPSE WEIGHT="0.1419" ORG_NEURODE="IN012" />					
			</NEURODE>
			<NEURODE N_ID="N005" ACTIVE="-1" ACTIVITY="0.0" BIAS="0.4853" CNAME="hidden 5" NNET_V4="0.0">
					<SYNAPSE WEIGHT="-0.4099" ORG_NEURODE="IN001" />
					<SYNAPSE WEIGHT="0.7439" ORG_NEURODE="IN002" />
					<SYNAPSE WEIGHT="0.9154" ORG_NEURODE="IN003" />
					<SYNAPSE WEIGHT="0.7412" ORG_NEURODE="IN004" />
					<SYNAPSE WEIGHT="0.0693" ORG_NEURODE="IN005" />
					<SYNAPSE WEIGHT="-0.1215" ORG_NEURODE="IN006" />
					<SYNAPSE WEIGHT="0.9206" ORG_NEURODE="IN007" />
					<SYNAPSE WEIGHT="0.4918" ORG_NEURODE="IN008" />
					<SYNAPSE WEIGHT="-0.2853" ORG_NEURODE="IN009" />
					<SYNAPSE WEIGHT="-0.6083" ORG_NEURODE="IN010" />
					<SYNAPSE WEIGHT="0.5201" ORG_NEURODE="IN011" />
					<SYNAPSE WEIGHT="0.9897" ORG_NEURODE="IN012" />					
			</NEURODE>
			<NEURODE N_ID="N006" ACTIVE="-1" ACTIVITY="0.0" BIAS="0.5458" CNAME="hidden 6" NNET_V4="0.0">
					<SYNAPSE WEIGHT="-0.8341" ORG_NEURODE="IN001" />
					<SYNAPSE WEIGHT="-0.2994" ORG_NEURODE="IN002" />
					<SYNAPSE WEIGHT="-0.3942" ORG_NEURODE="IN003" />
					<SYNAPSE WEIGHT="0.3036" ORG_NEURODE="IN004" />
					<SYNAPSE WEIGHT="0.1391" ORG_NEURODE="IN005" />
					<SYNAPSE WEIGHT="-0.4813" ORG_NEURODE="IN006" />
					<SYNAPSE WEIGHT="-0.1060" ORG_NEURODE="IN007" />
					<SYNAPSE WEIGHT="0.0088" ORG_NEURODE="IN008" />
					<SYNAPSE WEIGHT="0.0033" ORG_NEURODE="IN009" />
					<SYNAPSE WEIGHT="-0.8559" ORG_NEURODE="IN010" />
					<SYNAPSE WEIGHT="-0.2859" ORG_NEURODE="IN011" />
					<SYNAPSE WEIGHT="0.5009" ORG_NEURODE="IN012" />					
			</NEURODE>
			<NEURODE N_ID="N007" ACTIVE="-1" ACTIVITY="0.0" BIAS="0.7990" CNAME="hidden 7" NNET_V4="0.0">
					<SYNAPSE WEIGHT="-0.5446" ORG_NEURODE="IN001" />
					<SYNAPSE WEIGHT="-0.9147" ORG_NEURODE="IN002" />
					<SYNAPSE WEIGHT="-0.7763" ORG_NEURODE="IN003" />
					<SYNAPSE WEIGHT="0.0082" ORG_NEURODE="IN004" />
					<SYNAPSE WEIGHT="0.1817" ORG_NEURODE="IN005" />
					<SYNAPSE WEIGHT="-0.0715" ORG_NEURODE="IN006" />
					<SYNAPSE WEIGHT="-0.6505" ORG_NEURODE="IN007" />
					<SYNAPSE WEIGHT="0.9257" ORG_NEURODE="IN008" />
					<SYNAPSE WEIGHT="0.5791" ORG_NEURODE="IN009" />
					<SYNAPSE WEIGHT="-0.9687" ORG_NEURODE="IN010" />
					<SYNAPSE WEIGHT="-0.5411" ORG_NEURODE="IN011" />
					<SYNAPSE WEIGHT="0.9250" ORG_NEURODE="IN012" />					
			</NEURODE>
			<NEURODE N_ID="N008" ACTIVE="-1" ACTIVITY="0.0" BIAS="0.9133" CNAME="hidden 8" NNET_V4="0.0">
					<SYNAPSE WEIGHT="-0.9450" ORG_NEURODE="IN001" />
					<SYNAPSE WEIGHT="0.5888" ORG_NEURODE="IN002" />
					<SYNAPSE WEIGHT="-0.9410" ORG_NEURODE="IN003" />
					<SYNAPSE WEIGHT="0.9260" ORG_NEURODE="IN004" />
					<SYNAPSE WEIGHT="-0.7223" ORG_NEURODE="IN005" />
					<SYNAPSE WEIGHT="-0.5752" ORG_NEURODE="IN006" />
					<SYNAPSE WEIGHT="0.8846" ORG_NEURODE="IN007" />
					<SYNAPSE WEIGHT="0.3295" ORG_NEURODE="IN008" />
					<SYNAPSE WEIGHT="-0.6662" ORG_NEURODE="IN009" />
					<SYNAPSE WEIGHT="0.7099" ORG_NEURODE="IN010" />
					<SYNAPSE WEIGHT="-0.7717" ORG_NEURODE="IN011" />
					<SYNAPSE WEIGHT="-0.7958" ORG_NEURODE="IN012" />					
			</NEURODE>
			<NEURODE N_ID="N009" ACTIVE="-1" ACTIVITY="0.0" BIAS="0.0644" CNAME="hidden 9" NNET_V4="0.0">
					<SYNAPSE WEIGHT="0.3361" ORG_NEURODE="IN001" />
					<SYNAPSE WEIGHT="-0.6162" ORG_NEURODE="IN002" />
					<SYNAPSE WEIGHT="-0.1225" ORG_NEURODE="IN003" />
					<SYNAPSE WEIGHT="0.6351" ORG_NEURODE="IN004" />
					<SYNAPSE WEIGHT="-0.6479" ORG_NEURODE="IN005" />
					<SYNAPSE WEIGHT="0.7505" ORG_NEURODE="IN006" />
					<SYNAPSE WEIGHT="-0.3929" ORG_NEURODE="IN007" />
					<SYNAPSE WEIGHT="-0.4231" ORG_NEURODE="IN008" />
					<SYNAPSE WEIGHT="0.6907" ORG_NEURODE="IN009" />
					<SYNAPSE WEIGHT="0.5658" ORG_NEURODE="IN010" />
					<SYNAPSE WEIGHT="-0.6526" ORG_NEURODE="IN011" />
					<SYNAPSE WEIGHT="0.7126" ORG_NEURODE="IN012" />
			</NEURODE>
			<NEURODE N_ID="N010" ACTIVE="-1" ACTIVITY="0.0" BIAS="0.1893" CNAME="hidden 10" NNET_V4="0.0">
					<SYNAPSE WEIGHT="-0.8412" ORG_NEURODE="IN001" />
					<SYNAPSE WEIGHT="-0.5616" ORG_NEURODE="IN002" />
					<SYNAPSE WEIGHT="-0.1098" ORG_NEURODE="IN003" />
					<SYNAPSE WEIGHT="0.3490" ORG_NEURODE="IN004" />
					<SYNAPSE WEIGHT="-0.9553" ORG_NEURODE="IN005" />
					<SYNAPSE WEIGHT="0.1630" ORG_NEURODE="IN006" />
					<SYNAPSE WEIGHT="0.1141" ORG_NEURODE="IN007" />
					<SYNAPSE WEIGHT="-0.0422" ORG_NEURODE="IN008" />
					<SYNAPSE WEIGHT="-0.1544" ORG_NEURODE="IN009" />
					<SYNAPSE WEIGHT="-0.5565" ORG_NEURODE="IN010" />
					<SYNAPSE WEIGHT="0.9947" ORG_NEURODE="IN011" />
					<SYNAPSE WEIGHT="-0.8594" ORG_NEURODE="IN012" />					
			</NEURODE>
			<NEURODE N_ID="N011" ACTIVE="-1" ACTIVITY="0.0" BIAS="-0.9366" CNAME="hidden 11" NNET_V4="0.0">
					<SYNAPSE WEIGHT="-0.6148" ORG_NEURODE="IN001" />
					<SYNAPSE WEIGHT="0.1743" ORG_NEURODE="IN002" />
					<SYNAPSE WEIGHT="-0.4226" ORG_NEURODE="IN003" />
					<SYNAPSE WEIGHT="0.7447" ORG_NEURODE="IN004" />
					<SYNAPSE WEIGHT="0.7839" ORG_NEURODE="IN005" />
					<SYNAPSE WEIGHT="0.1408" ORG_NEURODE="IN006" />
					<SYNAPSE WEIGHT="-0.6429" ORG_NEURODE="IN007" />
					<SYNAPSE WEIGHT="-0.6763" ORG_NEURODE="IN008" />
					<SYNAPSE WEIGHT="-0.5833" ORG_NEURODE="IN009" />
					<SYNAPSE WEIGHT="0.4881" ORG_NEURODE="IN010" />
					<SYNAPSE WEIGHT="0.9553" ORG_NEURODE="IN011" />
					<SYNAPSE WEIGHT="0.2746" ORG_NEURODE="IN012" />					
			</NEURODE>
			<NEURODE N_ID="N012" ACTIVE="-1" ACTIVITY="0.0" BIAS="0.8776" CNAME="hidden 12" NNET_V4="0.0">
					<SYNAPSE WEIGHT="-0.6304" ORG_NEURODE="IN001" />
					<SYNAPSE WEIGHT="0.5909" ORG_NEURODE="IN002" />
					<SYNAPSE WEIGHT="0.1336" ORG_NEURODE="IN003" />
					<SYNAPSE WEIGHT="0.6676" ORG_NEURODE="IN004" />
					<SYNAPSE WEIGHT="-0.3656" ORG_NEURODE="IN005" />
					<SYNAPSE WEIGHT="-0.2637" ORG_NEURODE="IN006" />
					<SYNAPSE WEIGHT="-0.3563" ORG_NEURODE="IN007" />
					<SYNAPSE WEIGHT="0.1625" ORG_NEURODE="IN008" />
					<SYNAPSE WEIGHT="0.3891" ORG_NEURODE="IN009" />
					<SYNAPSE WEIGHT="-0.6782" ORG_NEURODE="IN010" />
					<SYNAPSE WEIGHT="-0.8236" ORG_NEURODE="IN011" />
					<SYNAPSE WEIGHT="-0.7185" ORG_NEURODE="IN012" />						
			</NEURODE>
			<NEURODE N_ID="N013" ACTIVE="-1" ACTIVITY="0.0" BIAS="-0.9785" CNAME="hidden 13" NNET_V4="0.0">
					<SYNAPSE WEIGHT="0.8865" ORG_NEURODE="IN001" />
					<SYNAPSE WEIGHT="-0.2614" ORG_NEURODE="IN002" />
					<SYNAPSE WEIGHT="0.6769" ORG_NEURODE="IN003" />
					<SYNAPSE WEIGHT="-0.6880" ORG_NEURODE="IN004" />
					<SYNAPSE WEIGHT="0.5587" ORG_NEURODE="IN005" />
					<SYNAPSE WEIGHT="-0.4735" ORG_NEURODE="IN006" />
					<SYNAPSE WEIGHT="-0.7062" ORG_NEURODE="IN007" />
					<SYNAPSE WEIGHT="0.3799" ORG_NEURODE="IN008" />
					<SYNAPSE WEIGHT="-0.2751" ORG_NEURODE="IN009" />
					<SYNAPSE WEIGHT="0.5912" ORG_NEURODE="IN010" />
					<SYNAPSE WEIGHT="0.5080" ORG_NEURODE="IN011" />
					<SYNAPSE WEIGHT="0.4683" ORG_NEURODE="IN012" />						
			</NEURODE>
			<NEURODE N_ID="N014" ACTIVE="-1" ACTIVITY="0.0" BIAS="0.0646" CNAME="hidden 14" NNET_V4="0.0">
					<SYNAPSE WEIGHT="0.6956" ORG_NEURODE="IN001" />
					<SYNAPSE WEIGHT="0.7733" ORG_NEURODE="IN002" />
					<SYNAPSE WEIGHT="-0.2074" ORG_NEURODE="IN003" />
					<SYNAPSE WEIGHT="0.5865" ORG_NEURODE="IN004" />
					<SYNAPSE WEIGHT="-0.7337" ORG_NEURODE="IN005" />
					<SYNAPSE WEIGHT="-0.7011" ORG_NEURODE="IN006" />
					<SYNAPSE WEIGHT="-0.9382" ORG_NEURODE="IN007" />
					<SYNAPSE WEIGHT="0.3728" ORG_NEURODE="IN008" />
					<SYNAPSE WEIGHT="0.1250" ORG_NEURODE="IN009" />
					<SYNAPSE WEIGHT="0.7236" ORG_NEURODE="IN010" />
					<SYNAPSE WEIGHT="-0.0433" ORG_NEURODE="IN011" />
					<SYNAPSE WEIGHT="-0.0429" ORG_NEURODE="IN012" />						
			</NEURODE>
			<NEURODE N_ID="N015" ACTIVE="-1" ACTIVITY="0.0" BIAS="-0.8588" CNAME="hidden 15" NNET_V4="0.0">
					<SYNAPSE WEIGHT="0.1029" ORG_NEURODE="IN001" />
					<SYNAPSE WEIGHT="0.8135" ORG_NEURODE="IN002" />
					<SYNAPSE WEIGHT="-0.2054" ORG_NEURODE="IN003" />
					<SYNAPSE WEIGHT="-0.2264" ORG_NEURODE="IN004" />
					<SYNAPSE WEIGHT="-0.5708" ORG_NEURODE="IN005" />
					<SYNAPSE WEIGHT="0.8923" ORG_NEURODE="IN006" />
					<SYNAPSE WEIGHT="-0.1485" ORG_NEURODE="IN007" />
					<SYNAPSE WEIGHT="0.1343" ORG_NEURODE="IN008" />
					<SYNAPSE WEIGHT="-0.3097" ORG_NEURODE="IN009" />
					<SYNAPSE WEIGHT="0.4314" ORG_NEURODE="IN010" />
					<SYNAPSE WEIGHT="-0.2098" ORG_NEURODE="IN011" />
					<SYNAPSE WEIGHT="0.3540" ORG_NEURODE="IN012" />	
			</NEURODE>
			<NEURODE N_ID="N016" ACTIVE="-1" ACTIVITY="0.0" BIAS="-0.3630" CNAME="hidden 16" NNET_V4="0.0">
					<SYNAPSE WEIGHT="-0.2945" ORG_NEURODE="IN001" />
					<SYNAPSE WEIGHT="0.2334" ORG_NEURODE="IN002" />
					<SYNAPSE WEIGHT="-0.9966" ORG_NEURODE="IN003" />
					<SYNAPSE WEIGHT="0.2012" ORG_NEURODE="IN004" />
					<SYNAPSE WEIGHT="0.9841" ORG_NEURODE="IN005" />
					<SYNAPSE WEIGHT="-0.3535" ORG_NEURODE="IN006" />
					<SYNAPSE WEIGHT="-0.4452" ORG_NEURODE="IN007" />
					<SYNAPSE WEIGHT="-0.9972" ORG_NEURODE="IN008" />
					<SYNAPSE WEIGHT="0.2721" ORG_NEURODE="IN009" />
					<SYNAPSE WEIGHT="0.8646" ORG_NEURODE="IN010" />
					<SYNAPSE WEIGHT="-0.4816" ORG_NEURODE="IN011" />
					<SYNAPSE WEIGHT="-0.0763" ORG_NEURODE="IN012" />	
			</NEURODE>
			<NEURODE N_ID="N017" ACTIVE="-1" ACTIVITY="0.0" BIAS="0.7941" CNAME="hidden 17" NNET_V4="0.0">
					<SYNAPSE WEIGHT="0.6575" ORG_NEURODE="IN001" />
					<SYNAPSE WEIGHT="0.7140" ORG_NEURODE="IN002" />
					<SYNAPSE WEIGHT="-0.2180" ORG_NEURODE="IN003" />
					<SYNAPSE WEIGHT="0.5650" ORG_NEURODE="IN004" />
					<SYNAPSE WEIGHT="0.2070" ORG_NEURODE="IN005" />
					<SYNAPSE WEIGHT="0.3154" ORG_NEURODE="IN006" />
					<SYNAPSE WEIGHT="0.5075" ORG_NEURODE="IN007" />
					<SYNAPSE WEIGHT="-0.7504" ORG_NEURODE="IN008" />
					<SYNAPSE WEIGHT="-0.8825" ORG_NEURODE="IN009" />
					<SYNAPSE WEIGHT="-0.3659" ORG_NEURODE="IN010" />
					<SYNAPSE WEIGHT="0.2736" ORG_NEURODE="IN011" />
					<SYNAPSE WEIGHT="0.2689" ORG_NEURODE="IN012" />	
			</NEURODE>
			<NEURODE N_ID="N018" ACTIVE="-1" ACTIVITY="0.0" BIAS="-0.7175" CNAME="hidden 18" NNET_V4="0.0">
					<SYNAPSE WEIGHT="-0.2027" ORG_NEURODE="IN001" />
					<SYNAPSE WEIGHT="0.9808" ORG_NEURODE="IN002" />
					<SYNAPSE WEIGHT="-0.1866" ORG_NEURODE="IN003" />
					<SYNAPSE WEIGHT="-0.7173" ORG_NEURODE="IN004" />
					<SYNAPSE WEIGHT="-0.0966" ORG_NEURODE="IN005" />
					<SYNAPSE WEIGHT="0.1749" ORG_NEURODE="IN006" />
					<SYNAPSE WEIGHT="0.4099" ORG_NEURODE="IN007" />
					<SYNAPSE WEIGHT="-0.2672" ORG_NEURODE="IN008" />
					<SYNAPSE WEIGHT="0.1239" ORG_NEURODE="IN009" />
					<SYNAPSE WEIGHT="0.7192" ORG_NEURODE="IN010" />
					<SYNAPSE WEIGHT="-0.0191" ORG_NEURODE="IN011" />
					<SYNAPSE WEIGHT="-0.0841" ORG_NEURODE="IN012" />	
			</NEURODE>
			<NEURODE N_ID="N019" ACTIVE="-1" ACTIVITY="0.0" BIAS="-0.0081" CNAME="hidden 19" NNET_V4="0.0">
					<SYNAPSE WEIGHT="-0.2299" ORG_NEURODE="IN001" />
					<SYNAPSE WEIGHT="-0.5270" ORG_NEURODE="IN002" />
					<SYNAPSE WEIGHT="-0.7054" ORG_NEURODE="IN003" />
					<SYNAPSE WEIGHT="0.8963" ORG_NEURODE="IN004" />
					<SYNAPSE WEIGHT="-0.9180" ORG_NEURODE="IN005" />
					<SYNAPSE WEIGHT="-0.6553" ORG_NEURODE="IN006" />
					<SYNAPSE WEIGHT="-0.8588" ORG_NEURODE="IN007" />
					<SYNAPSE WEIGHT="0.8422" ORG_NEURODE="IN008" />
					<SYNAPSE WEIGHT="0.9210" ORG_NEURODE="IN009" />
					<SYNAPSE WEIGHT="-0.4363" ORG_NEURODE="IN010" />
					<SYNAPSE WEIGHT="-0.9470" ORG_NEURODE="IN011" />
					<SYNAPSE WEIGHT="-0.9729" ORG_NEURODE="IN012" />	
			</NEURODE>
			<NEURODE N_ID="N020" ACTIVE="-1" ACTIVITY="0.0" BIAS="-0.3206" CNAME="hidden 20" NNET_V4="0.0">
					<SYNAPSE WEIGHT="0.9558" ORG_NEURODE="IN001" />
					<SYNAPSE WEIGHT="0.5616" ORG_NEURODE="IN002" />
					<SYNAPSE WEIGHT="0.0200" ORG_NEURODE="IN003" />
					<SYNAPSE WEIGHT="0.9515" ORG_NEURODE="IN004" />
					<SYNAPSE WEIGHT="0.4079" ORG_NEURODE="IN005" />
					<SYNAPSE WEIGHT="0.6951" ORG_NEURODE="IN006" />
					<SYNAPSE WEIGHT="0.3424" ORG_NEURODE="IN007" />
					<SYNAPSE WEIGHT="-0.7412" ORG_NEURODE="IN008" />
					<SYNAPSE WEIGHT="-0.3027" ORG_NEURODE="IN009" />
					<SYNAPSE WEIGHT="0.1282" ORG_NEURODE="IN010" />
					<SYNAPSE WEIGHT="0.6632" ORG_NEURODE="IN011" />
					<SYNAPSE WEIGHT="0.4536" ORG_NEURODE="IN012" />	
			</NEURODE>
			<NEURODE N_ID="N021" ACTIVE="-1" ACTIVITY="0.0" BIAS="0.4695" CNAME="hidden 21" NNET_V4="0.0">
					<SYNAPSE WEIGHT="0.4059" ORG_NEURODE="IN001" />
					<SYNAPSE WEIGHT="-0.4571" ORG_NEURODE="IN002" />
					<SYNAPSE WEIGHT="0.5094" ORG_NEURODE="IN003" />
					<SYNAPSE WEIGHT="0.8216" ORG_NEURODE="IN004" />
					<SYNAPSE WEIGHT="-0.7319" ORG_NEURODE="IN005" />
					<SYNAPSE WEIGHT="0.0926" ORG_NEURODE="IN006" />
					<SYNAPSE WEIGHT="-0.5621" ORG_NEURODE="IN007" />
					<SYNAPSE WEIGHT="0.4664" ORG_NEURODE="IN008" />
					<SYNAPSE WEIGHT="-0.6458" ORG_NEURODE="IN009" />
					<SYNAPSE WEIGHT="0.7565" ORG_NEURODE="IN010" />
					<SYNAPSE WEIGHT="-0.4806" ORG_NEURODE="IN011" />
					<SYNAPSE WEIGHT="-0.3959" ORG_NEURODE="IN012" />	
			</NEURODE>
			<NEURODE N_ID="N022" ACTIVE="-1" ACTIVITY="0.0" BIAS="-0.5888" CNAME="hidden 22" NNET_V4="0.0">
					<SYNAPSE WEIGHT="-0.0635" ORG_NEURODE="IN001" />
					<SYNAPSE WEIGHT="0.7550" ORG_NEURODE="IN002" />
					<SYNAPSE WEIGHT="-0.3080" ORG_NEURODE="IN003" />
					<SYNAPSE WEIGHT="0.4077" ORG_NEURODE="IN004" />
					<SYNAPSE WEIGHT="0.8700" ORG_NEURODE="IN005" />
					<SYNAPSE WEIGHT="-0.6788" ORG_NEURODE="IN006" />
					<SYNAPSE WEIGHT="-0.2499" ORG_NEURODE="IN007" />
					<SYNAPSE WEIGHT="0.4406" ORG_NEURODE="IN008" />
					<SYNAPSE WEIGHT="-0.6170" ORG_NEURODE="IN009" />
					<SYNAPSE WEIGHT="0.4313" ORG_NEURODE="IN010" />
					<SYNAPSE WEIGHT="0.1532" ORG_NEURODE="IN011" />
					<SYNAPSE WEIGHT="-0.8525" ORG_NEURODE="IN012" />	
			</NEURODE>
			<NEURODE N_ID="N023" ACTIVE="-1" ACTIVITY="0.0" BIAS="0.1893" CNAME="hidden 23" NNET_V4="0.0">
					<SYNAPSE WEIGHT="-0.2666" ORG_NEURODE="IN001" />
					<SYNAPSE WEIGHT="-0.0959" ORG_NEURODE="IN002" />
					<SYNAPSE WEIGHT="-0.2805" ORG_NEURODE="IN003" />
					<SYNAPSE WEIGHT="-0.3217" ORG_NEURODE="IN004" />
					<SYNAPSE WEIGHT="-0.9527" ORG_NEURODE="IN005" />
					<SYNAPSE WEIGHT="0.1198" ORG_NEURODE="IN006" />
					<SYNAPSE WEIGHT="0.6526" ORG_NEURODE="IN007" />
					<SYNAPSE WEIGHT="-0.4994" ORG_NEURODE="IN008" />
					<SYNAPSE WEIGHT="-0.0632" ORG_NEURODE="IN009" />
					<SYNAPSE WEIGHT="0.5899" ORG_NEURODE="IN010" />
					<SYNAPSE WEIGHT="-0.1788" ORG_NEURODE="IN011" />
					<SYNAPSE WEIGHT="0.6633" ORG_NEURODE="IN012" />	
			</NEURODE>
			<NEURODE N_ID="N024" ACTIVE="-1" ACTIVITY="0.0" BIAS="0.0815" CNAME="hidden 24" NNET_V4="0.0">
					<SYNAPSE WEIGHT="0.8973" ORG_NEURODE="IN001" />
					<SYNAPSE WEIGHT="-0.9856" ORG_NEURODE="IN002" />
					<SYNAPSE WEIGHT="0.3567" ORG_NEURODE="IN003" />
					<SYNAPSE WEIGHT="0.0364" ORG_NEURODE="IN004" />
					<SYNAPSE WEIGHT="0.1857" ORG_NEURODE="IN005" />
					<SYNAPSE WEIGHT="0.6776" ORG_NEURODE="IN006" />
					<SYNAPSE WEIGHT="0.4399" ORG_NEURODE="IN007" />
					<SYNAPSE WEIGHT="-0.2128" ORG_NEURODE="IN008" />
					<SYNAPSE WEIGHT="-0.1521" ORG_NEURODE="IN009" />
					<SYNAPSE WEIGHT="0.5645" ORG_NEURODE="IN010" />
					<SYNAPSE WEIGHT="-0.3984" ORG_NEURODE="IN011" />
					<SYNAPSE WEIGHT="0.9545" ORG_NEURODE="IN012" />	
			</NEURODE>
			<NEURODE N_ID="N025" ACTIVE="-1" ACTIVITY="0.0" BIAS="-0.6909" CNAME="hidden 25" NNET_V4="0.0">
					<SYNAPSE WEIGHT="0.6055" ORG_NEURODE="IN001" />
					<SYNAPSE WEIGHT="0.2495" ORG_NEURODE="IN002" />
					<SYNAPSE WEIGHT="-0.1854" ORG_NEURODE="IN003" />
					<SYNAPSE WEIGHT="-0.1619" ORG_NEURODE="IN004" />
					<SYNAPSE WEIGHT="-0.9010" ORG_NEURODE="IN005" />
					<SYNAPSE WEIGHT="0.6498" ORG_NEURODE="IN006" />
					<SYNAPSE WEIGHT="-0.2303" ORG_NEURODE="IN007" />
					<SYNAPSE WEIGHT="-0.6194" ORG_NEURODE="IN008" />
					<SYNAPSE WEIGHT="0.7498" ORG_NEURODE="IN009" />
					<SYNAPSE WEIGHT="-0.9227" ORG_NEURODE="IN010" />
					<SYNAPSE WEIGHT="0.1039" ORG_NEURODE="IN011" />
					<SYNAPSE WEIGHT="0.8859" ORG_NEURODE="IN012" />	
			</NEURODE>	
			<NEURODE N_ID="N026" ACTIVE="-1" ACTIVITY="0.0" BIAS="0.9715" CNAME="hidden 26" NNET_V4="0.0">
					<SYNAPSE WEIGHT="0.1860" ORG_NEURODE="IN001" />
					<SYNAPSE WEIGHT="-0.5038" ORG_NEURODE="IN002" />
					<SYNAPSE WEIGHT="-0.2974" ORG_NEURODE="IN003" />
					<SYNAPSE WEIGHT="0.3206" ORG_NEURODE="IN004" />
					<SYNAPSE WEIGHT="0.6716" ORG_NEURODE="IN005" />
					<SYNAPSE WEIGHT="0.4849" ORG_NEURODE="IN006" />
					<SYNAPSE WEIGHT="0.1334" ORG_NEURODE="IN007" />
					<SYNAPSE WEIGHT="0.5742" ORG_NEURODE="IN008" />
					<SYNAPSE WEIGHT="-0.0615" ORG_NEURODE="IN009" />
					<SYNAPSE WEIGHT="0.8352" ORG_NEURODE="IN010" />
					<SYNAPSE WEIGHT="0.2185" ORG_NEURODE="IN011" />
					<SYNAPSE WEIGHT="-0.2231" ORG_NEURODE="IN012" />	
			</NEURODE>				
		</LAYER>
		<LAYER LAYER_NAME="OUTPUT" TRANSFER_FUNCTION="2">
			<NEURODE N_ID="ON001" ACTIVE="-1" ACTIVITY="0.0" BIAS="0.0205" CNAME="Home Team Win" NNET_V4="0.0">
					<SYNAPSE WEIGHT="0.2072" ORG_NEURODE="N001" />
					<SYNAPSE WEIGHT="-0.0976" ORG_NEURODE="N002" />
					<SYNAPSE WEIGHT="0.2859" ORG_NEURODE="N003" />
					<SYNAPSE WEIGHT="-0.9914" ORG_NEURODE="N004" />
					<SYNAPSE WEIGHT="-0.8344" ORG_NEURODE="N005" />
					<SYNAPSE WEIGHT="-0.3995" ORG_NEURODE="N006" />
					<SYNAPSE WEIGHT="-0.8693" ORG_NEURODE="N007" />
					<SYNAPSE WEIGHT="0.7837" ORG_NEURODE="N008" />
					<SYNAPSE WEIGHT="-0.4488" ORG_NEURODE="N009" />
					<SYNAPSE WEIGHT="-0.0887" ORG_NEURODE="N010" />
					<SYNAPSE WEIGHT="0.3596" ORG_NEURODE="N011" />
					<SYNAPSE WEIGHT="0.0385" ORG_NEURODE="N012" />
					<SYNAPSE WEIGHT="0.2365" ORG_NEURODE="N013" />
					<SYNAPSE WEIGHT="0.9601" ORG_NEURODE="N014" />
					<SYNAPSE WEIGHT="0.1611" ORG_NEURODE="N015" />
					<SYNAPSE WEIGHT="0.0862" ORG_NEURODE="N016" />
					<SYNAPSE WEIGHT="-0.1756" ORG_NEURODE="N017" />
					<SYNAPSE WEIGHT="-0.1769" ORG_NEURODE="N018" />
					<SYNAPSE WEIGHT="0.3573" ORG_NEURODE="N019" />
					<SYNAPSE WEIGHT="-0.3583" ORG_NEURODE="N020" />
					<SYNAPSE WEIGHT="0.3607" ORG_NEURODE="N021" />
					<SYNAPSE WEIGHT="-0.3213" ORG_NEURODE="N022" />
					<SYNAPSE WEIGHT="0.1779" ORG_NEURODE="N023" />
					<SYNAPSE WEIGHT="0.8776" ORG_NEURODE="N024" />
					<SYNAPSE WEIGHT="-0.6473" ORG_NEURODE="N025" />
					<SYNAPSE WEIGHT="-0.5524" ORG_NEURODE="N026" />					
			</NEURODE>
			<NEURODE N_ID="ON002" ACTIVE="-1" ACTIVITY="0.0" BIAS="-0.4564" CNAME="Away Team Win" NNET_V4="0.0">
					<SYNAPSE WEIGHT="0.6931" ORG_NEURODE="N001" />
					<SYNAPSE WEIGHT="-0.0691" ORG_NEURODE="N002" />
					<SYNAPSE WEIGHT="0.7366" ORG_NEURODE="N003" />
					<SYNAPSE WEIGHT="-0.8052" ORG_NEURODE="N004" />
					<SYNAPSE WEIGHT="-0.3401" ORG_NEURODE="N005" />
					<SYNAPSE WEIGHT="-0.7476" ORG_NEURODE="N006" />
					<SYNAPSE WEIGHT="0.6667" ORG_NEURODE="N007" />
					<SYNAPSE WEIGHT="-0.2211" ORG_NEURODE="N008" />
					<SYNAPSE WEIGHT="0.2008" ORG_NEURODE="N009" />
					<SYNAPSE WEIGHT="-0.9528" ORG_NEURODE="N010" />
					<SYNAPSE WEIGHT="0.3037" ORG_NEURODE="N011" />
					<SYNAPSE WEIGHT="0.8843" ORG_NEURODE="N012" />
					<SYNAPSE WEIGHT="-0.1001" ORG_NEURODE="N013" />
					<SYNAPSE WEIGHT="0.7738" ORG_NEURODE="N013" />
					<SYNAPSE WEIGHT="-0.8094" ORG_NEURODE="N014" />
					<SYNAPSE WEIGHT="-0.2960" ORG_NEURODE="N015" />
					<SYNAPSE WEIGHT="0.9963" ORG_NEURODE="N016" />
					<SYNAPSE WEIGHT="0.4765" ORG_NEURODE="N017" />
					<SYNAPSE WEIGHT="0.7547" ORG_NEURODE="N018" />
					<SYNAPSE WEIGHT="0.3379" ORG_NEURODE="N019" />
					<SYNAPSE WEIGHT="0.1977" ORG_NEURODE="N020" />
					<SYNAPSE WEIGHT="0.9493" ORG_NEURODE="N021" />
					<SYNAPSE WEIGHT="0.0704" ORG_NEURODE="N022" />
					<SYNAPSE WEIGHT="-0.3810" ORG_NEURODE="N023" />
					<SYNAPSE WEIGHT="0.2069" ORG_NEURODE="N024" />
					<SYNAPSE WEIGHT="0.9931" ORG_NEURODE="N025" />
					<SYNAPSE WEIGHT="-0.3365" ORG_NEURODE="N026" />						
			</NEURODE>			
		</LAYER>
	</SUBNET>
</NNETWORK>
